LICENSE
MANIFEST.in
NOTICE
README.md
setup.py
acvtool/__init__.py
acvtool/acvtool.py
acvtool.egg-info/PKG-INFO
acvtool.egg-info/SOURCES.txt
acvtool.egg-info/dependency_links.txt
acvtool.egg-info/entry_points.txt
acvtool.egg-info/requires.txt
acvtool.egg-info/top_level.txt
acvtool/cutter/__init__.py
acvtool/cutter/basic_block.py
acvtool/cutter/classes.py
acvtool/cutter/cutter.py
acvtool/cutter/invokes.py
acvtool/cutter/label_block.py
acvtool/cutter/methods.py
acvtool/cutter/returns.py
acvtool/cutter/shrinker.py
acvtool/smiler/__init__.py
acvtool/smiler/acv.py
acvtool/smiler/cliparser.py
acvtool/smiler/config.py
acvtool/smiler/granularity.py
acvtool/smiler/smiler.py
acvtool/smiler/entities/__init__.py
acvtool/smiler/entities/coverage.py
acvtool/smiler/entities/wd.py
acvtool/smiler/instrumenting/__init__.py
acvtool/smiler/instrumenting/acvpatcher.py
acvtool/smiler/instrumenting/android_manifest.py
acvtool/smiler/instrumenting/baksmali.py
acvtool/smiler/instrumenting/config.py
acvtool/smiler/instrumenting/smali_instrumenter.py
acvtool/smiler/instrumenting/utils.py
acvtool/smiler/instrumenting/zipper.py
acvtool/smiler/instrumenting/apkil/__init__.py
acvtool/smiler/instrumenting/apkil/arraydatanode.py
acvtool/smiler/instrumenting/apkil/classnode.py
acvtool/smiler/instrumenting/apkil/codeblocknode.py
acvtool/smiler/instrumenting/apkil/constants.py
acvtool/smiler/instrumenting/apkil/fieldnode.py
acvtool/smiler/instrumenting/apkil/insn35c.py
acvtool/smiler/instrumenting/apkil/insn3rc.py
acvtool/smiler/instrumenting/apkil/insnnode.py
acvtool/smiler/instrumenting/apkil/labelnode.py
acvtool/smiler/instrumenting/apkil/methodnode.py
acvtool/smiler/instrumenting/apkil/smalitree.py
acvtool/smiler/instrumenting/apkil/switchnode.py
acvtool/smiler/instrumenting/apkil/trynode.py
acvtool/smiler/instrumenting/apkil/typenode.py
acvtool/smiler/instrumenting/core/__init__.py
acvtool/smiler/instrumenting/core/acv_classes.py
acvtool/smiler/instrumenting/core/class_instrumenter.py
acvtool/smiler/instrumenting/core/method_instrumenter.py
acvtool/smiler/libs/__init__.py
acvtool/smiler/libs/libs.py
acvtool/smiler/libs/jars/__init__.py
