Metadata-Version: 2.4
Name: acvtool
Version: 2.3.5
Summary: ACVTool is an instrumentation-based tool to measure and visualize instruction coverage for Android apps.
Home-page: https://github.com/pilgun/acvtool
Author: Aleksandr Pilgun
Author-email: alexand.pilgun@gmail.com
Classifier: Development Status :: 5 - Production/Stable
Classifier: Intended Audience :: Developers
Classifier: License :: OSI Approved :: Apache Software License
Classifier: Programming Language :: Python :: 3.13
License-File: LICENSE
License-File: NOTICE
Requires-Dist: PyYAML==6.0.1
Requires-Dist: Chameleon==4.5.4
Requires-Dist: javaobj-py3==0.4.4
Requires-Dist: setuptools<81
Requires-Dist: lxml==5.4.0
Dynamic: author
Dynamic: author-email
Dynamic: classifier
Dynamic: home-page
Dynamic: license-file
Dynamic: requires-dist
Dynamic: summary
